python_to_cpp/__init__.py
python_to_cpp/__main__ .py
python_to_cpp/ast_parser.py
python_to_cpp/ast_to_cpp_converter.py
python_to_cpp/codegen.py
python_to_cpp/transpiler.py
python_to_cpp-0.1.8.dist-info/METADATA
python_to_cpp-0.1.8.dist-info/WHEEL
python_to_cpp-0.1.8.dist-info/entry_points.txt
python_to_cpp-0.1.8.dist-info/top_level.txt
python_to_cpp-0.1.8.dist-info/RECORD
