Metadata-Version: 2.4
Name: python_to_cpp
Version: 0.1.8
Summary: Convert Python To C++
Home-page: https://github.com/Singhom931/python_to_cpp
Author: Singhom931
Dynamic: author
Dynamic: description-content-type
Dynamic: home-page
Dynamic: summary
